jupydocs/__init__.py
jupydocs/numpydocstring.py
jupydocs-0.1.2.dist-info/LICENSE
jupydocs-0.1.2.dist-info/WHEEL
jupydocs-0.1.2.dist-info/METADATA
jupydocs-0.1.2.dist-info/RECORD
