Metadata-Version: 2.1
Name: jupydocs
Version: 0.1.2
Summary: Easy Python package documentation using markdown and jupyter
Home-page: https://github.com/SamEdwardes/jupydocs
License: MIT
Keywords: python,docs,documentation
Author: SamEdwardes
Author-email: edwardes.s@gmail.com
Requires-Python: >=3.7,<4.0
Classifier: License :: OSI Approved :: MIT License
Classifier: Programming Language :: Python :: 3
Classifier: Programming Language :: Python :: 3.7
Classifier: Programming Language :: Python :: 3.8
Classifier: Programming Language :: Python :: 3.9
Requires-Dist: ipython (>=7.19.0,<8.0.0)
Requires-Dist: tabulate (>=0.8.7,<0.9.0)
Project-URL: Documentation, https://jupydocs.netlify.app/
Project-URL: Repository, https://github.com/SamEdwardes/jupydocs
